meilisearch_fastapi/__init__.py
meilisearch_fastapi/_client.py
meilisearch_fastapi/_config.py
meilisearch_fastapi/models/__init__.py
meilisearch_fastapi/models/document_info.py
meilisearch_fastapi/models/index.py
meilisearch_fastapi/models/search_parameters.py
meilisearch_fastapi/models/settings.py
meilisearch_fastapi/models/tenant_token.py
meilisearch_fastapi/py.typed
meilisearch_fastapi/routes/__init__.py
meilisearch_fastapi/routes/document_routes.py
meilisearch_fastapi/routes/index_routes.py
meilisearch_fastapi/routes/meilisearch_routes.py
meilisearch_fastapi/routes/search_routes.py
meilisearch_fastapi/routes/settings_routes.py
meilisearch_fastapi-0.21.1.dist-info/LICENSE
meilisearch_fastapi-0.21.1.dist-info/METADATA
meilisearch_fastapi-0.21.1.dist-info/WHEEL
meilisearch_fastapi-0.21.1.dist-info/RECORD
