Metadata-Version: 2.3
Name: meilisearch-fastapi
Version: 0.21.1
Summary: Meilisearch integration with FastAPI
License: MIT
Keywords: meilisearch,fastapi,async,search
Author: Paul Sanders
Author-email: psanders1@gmail.com
Requires-Python: >=3.9,<4.0
Classifier: Development Status :: 7 - Inactive
Classifier: License :: OSI Approved :: MIT License
Classifier: Operating System :: OS Independent
Classifier: Programming Language :: Python :: 3
Classifier: Programming Language :: Python :: 3.9
Classifier: Programming Language :: Python :: 3.10
Classifier: Programming Language :: Python :: 3.11
Classifier: Programming Language :: Python :: 3.12
Classifier: Programming Language :: Python :: 3.13
Requires-Dist: camel-converter (>=3.0.2)
Requires-Dist: eval-type-backport (>=0.2.0) ; python_version < "3.10"
Requires-Dist: fastapi (>=0.95.1)
Requires-Dist: meilisearch-python-sdk (>=3.0.0)
Requires-Dist: pydantic (>=2.0.0)
Requires-Dist: pydantic-settings (>=2.0.3)
Project-URL: Documentation, https://github.com/sanders41/meilisearch-fastapi
Project-URL: Homepage, https://github.com/sanders41/meilisearch-fastapi
Project-URL: Repository, https://github.com/sanders41/meilisearch-fastapi
